PyChromeController/PyChromeController.py
PyChromeController/__init__.py
PyChromeController-0.1.4.dist-info/LICENSE
PyChromeController-0.1.4.dist-info/METADATA
PyChromeController-0.1.4.dist-info/WHEEL
PyChromeController-0.1.4.dist-info/top_level.txt
PyChromeController-0.1.4.dist-info/RECORD
