Metadata-Version: 2.1
Name: PyChromeController
Version: 0.1.4
Summary: A Python package to control Chrome browser actions.
Home-page: https://github.com/Michdo93/PyChromeController
Author: Michael Christian Dörflinger
Author-email: michaeldoerflinger93@gamil.com
License: MIT
Classifier: Programming Language :: Python :: 3
Classifier: License :: OSI Approved :: MIT License
Classifier: Operating System :: OS Independent
Requires-Python: >=3.6
License-File: LICENSE
Requires-Dist: selenium>=4.0.0
Requires-Dist: pyautogui>=0.9.50
Requires-Dist: pyperclip>=1.8.2
